mp2signal/__init__.py
mp2signal/mp2s.py
mp2signal/relaxed_face.joblib
mp2signal-0.0.2.dist-info/METADATA
mp2signal-0.0.2.dist-info/WHEEL
mp2signal-0.0.2.dist-info/licenses/LICENSE
mp2signal-0.0.2.dist-info/RECORD
