Metadata-Version: 2.1
Name: mp2signal
Version: 0.0.2
Summary: Normalizes the mediapipe pose in 3d space based on body proportions and returns joint angles.
Project-URL: Homepage, https://github.com/vskobov/mp2signal
Author-email: Victor Skobov <vskobov@gmail.com>
License-File: LICENSE
Classifier: Development Status :: 5 - Production/Stable
Classifier: Intended Audience :: Science/Research
Classifier: License :: OSI Approved :: GNU Affero General Public License v3 or later (AGPLv3+)
Classifier: Operating System :: OS Independent
Classifier: Programming Language :: Python :: 3
Classifier: Topic :: Scientific/Engineering
Requires-Python: >=3.9
Requires-Dist: joblib
Requires-Dist: mediapipe
Requires-Dist: numpy
Requires-Dist: opencv-python
